deltaframe/__init__.py
deltaframe/_nbdev.py
deltaframe/core.py
deltaframe-0.0.6.dist-info/LICENSE
deltaframe-0.0.6.dist-info/METADATA
deltaframe-0.0.6.dist-info/WHEEL
deltaframe-0.0.6.dist-info/entry_points.txt
deltaframe-0.0.6.dist-info/top_level.txt
deltaframe-0.0.6.dist-info/RECORD
